simple_notifs/__init__.py
simple_notifs/simple_notifs.py
simple_notifs-0.0.3.dist-info/METADATA
simple_notifs-0.0.3.dist-info/WHEEL
simple_notifs-0.0.3.dist-info/licenses/LICENSE
simple_notifs-0.0.3.dist-info/RECORD
