Metadata-Version: 2.1
Name: simple_notifs
Version: 0.0.3
Summary: A python library for creating simple, shortened notification time deltas. This is specifically helpful when time differences like `1h` or `2w` are needed to show a how long something has existed as of right now.
Project-URL: Homepage, https://github.com/nicosanc/simple_notifs
Project-URL: Bug Tracker, https://github.com/nicosanc/simple_notif/issues
Author-email: Nico Sanchez <nicosanchez0411@gmail.com>
License-File: LICENSE
Classifier: License :: OSI Approved :: MIT License
Classifier: Operating System :: OS Independent
Classifier: Programming Language :: Python :: 3
Requires-Python: >=3.7
Requires-Dist: arrow
